Workbook

Sheet Sheet1
A1: Ticker | B1: Asset Class Sistema | C1: Asset Class | D1: Geography / Subclass | E1: Indice | F1: Market
A2: 0JKT LN EQUITY | B2: RENTA VARIABLE | C2: RENTA VARIABLE | D2: Asia ex-Japan | E2: ISHARES TRUST ISHARES MSCI INDIA ETF | F2: India
A3: AAXJ US EQUITY | B3: RENTA VARIABLE | C3: RENTA VARIABLE | D3: Asia ex-Japan | E3: ISHARES MSCI ALL COUNTRY ASIA ES Japan | F3: General
A4: ABCHNSA LX EQUITY | B4: RENTA VARIABLE | C4: RENTA VARIABLE | D4: Asia ex-Japan | E4: AB SICAV I CHINA A SHARES EQUITY PORTFOLIO | F4: China
A5: BGFPABA LN EQUITY | B5: RENTA VARIABLE | C5: RENTA VARIABLE | D5: Asia ex-Japan | E5: BAILLIE GIFFORD OVERSEAS GROWTH FUNDS ICVC BAILLIE GIFFORD PACIFIC FUND | F5: General
A6: CPXJ LN EQUITY | B6: RENTA VARIABLE | C6: RENTA VARIABLE | D6: Asia ex-Japan | E6: ISHARES MSCI PACIFIC EX Japan UCITS ETF | F6: General
A7: CAFINIV LX EQUITY | B7: RENTA VARIABLE | C7: RENTA VARIABLE | D7: Asia ex-Japan | E7: AMUNDI FUNDS SBI FM INDIA EQUITY | F7: India
A8: FFASAIU LX EQUITY | B8: RENTA VARIABLE | C8: RENTA VARIABLE | D8: Asia ex-Japan | E8: FIDELITY FUNDS ASEAN FUND | F8: General
A9: FFEMASI LX EQUITY | B9: RENTA VARIABLE | C9: RENTA VARIABLE | D9: Asia ex-Japan | E9: FIDELITY FUNDS EMERGING ASIA FUND | F9: General
A10: FIASCIU LX EQUITY | B10: RENTA VARIABLE | C10: RENTA VARIABLE | D10: Asia ex-Japan | E10: FIDELITY FUNDS ASIAN SMALLER COMPANIES FUND | F10: General
A11: GMF US EQUITY | B11: RENTA VARIABLE | C11: RENTA VARIABLE | D11: Asia ex-Japan | E11: SPDR INDEX SHARES FUNDS SPDR SP EMERGING ASIA PACIFIC ETF | F11: General
A12: FRAINIA LX EQUITY | B12: RENTA VARIABLE | C12: RENTA VARIABLE | D12: Asia ex-Japan | E12: FRANKLIN TEMPLETON INVESTMENT FUND FRANKLIN INDIA FUND | F12: India
... A337: CH0008742519 | B337: RENTA VARIABLE | C337: RENTA VARIABLE | D337: Swiss | E337: Swisscom Rg | F337: Stock
A338: AELCAEC LX EQUITY
A339: MLATAMD KY EQUITY
A340: MXAPJ Index
A341: MXEUG Index
A342: MXJP Index
A343: MXLA Index
A344: SPX Index
A345: UKX Index
A346: XLC US EQUITY | B346: RENTA VARIABLE | C346: RENTA VARIABLE | D346: United States | E346: THE SELECT SECTOR SPDR TRUST THE COMMUNICATION SERVICES SELECT SECTOR SPDR FUND | F346: Sector
A347: XAR US EQUITY | B347: RENTA VARIABLE | C347: RENTA VARIABLE | D347: United States | E347: SPDR S&P AEROSPACE & DEFENSE ETF | F347: Sector
A348: XLI US EQUITY | B348: RENTA VARIABLE | C348: RENTA VARIABLE | D348: United States | E348: THE SELECT SECTOR SPDR TRUST THE INDUSTRIAL SELECT SECTOR SPDR FUND | F348: Sector
A349: SPYG US EQUITY | B349: RENTA VARIABLE | C349: RENTA VARIABLE | D349: United States | E349: SPDR SERIES TRUST SPDR PORTFOLIO S&P 500 GROWTH ETF | F349: General
A350: VTI US EQUITY | B350: RENTA VARIABLE | C350: RENTA VARIABLE | D350: United States | E350: VANGUARD INDEX FUNDS VANGUARD TOTAL STOCK MARKET ETF | F350: General
A351: QQQM US EQUITY | B351: RENTA VARIABLE | C351: RENTA VARIABLE | D351: United States | E351: INVESCO EXCHANGE TRADED FUND TRUST II INVESCO NASDAQ 100 ETF | F351: General
A352: VUG US EQUITY | B352: RENTA VARIABLE | C352: RENTA VARIABLE | D352: United States | E352: VANGUARD INDEX FUNDS VANGUARD GROWTH ETF | F352: Sector
A353: VOX US EQUITY | B353: RENTA VARIABLE | C353: RENTA VARIABLE | D353: United States | E353: VANGUARD COMMUNICATION SERVICES INDEX FUND ETF | F353: Sector
A354: ESGV US EQUITY | B354: RENTA VARIABLE | C354: RENTA VARIABLE | D354: United States | E354: VANGUARD ESG US STOCK ETF | F354: General
A355: CSNDX SW EQUITY | B355: RENTA VARIABLE | C355: RENTA VARIABLE | D355: United States | E355: ISHARES NASDAQ 100 USD ACC | F355: General
A356: IWF US EQUITY | B356: RENTA VARIABLE | C356: RENTA VARIABLE | D356: United States | E356: ISHARES TRUST ISHARES RUSSELL 1000 GROWTH ETF | F356: Small Cap
A357: IYW US EQUITY | B357: RENTA VARIABLE | C357: RENTA VARIABLE | D357: United States | E357: ISHARES DJ TECHNOLOGY | F357: Sector
... A598: XDAX GR EQUITY | B598: RENTA VARIABLE | C598: RENTA VARIABLE | D598: Europe ex UK | E598: XTRACKERS DAX UCITS ETF | F598: Germany

Sheet Hoja1
A1: Estan | B1: Ticker | C1: Nombre | D1: Moneda | E1: System Asset Class | F1: Portafolio | G1: Asset Class | H1: Geography / Subclass | I1: Market
A2: =VLOOKUP(B2,Sheet1!$A$1:$B$415,1,FALSE) -> #N/A | B2: ARISTEIA INTERNATIONAL LIMITED CLASS G SHARES | C2: ARISTEIA INTERNATIONAL LIMITED CLASS G SHARES HOLDBACK | D2: USD - United States Dollar | E2: PRIVATE EQUITY | F2: Internacional | G2: Alternative | H2: Private Equity | I2: Private Equity
A3: =VLOOKUP(B3,Sheet1!$A$1:$B$415,1,FALSE) -> #N/A | B3: CDNS US EQUITY | C3: CADENCE DESIGN SYSTEMS | D3: USD - United States Dollar | E3: RENTA VARIABLE | F3: Internacional | G3: Equities | H3: USA | I3: Stock
A4: =VLOOKUP(B4,Sheet1!$A$1:$B$415,1,FALSE) -> #N/A | B4: DPZ US EQUITY | C4: DOMINOS PIZZA INC | D4: USD - United States Dollar | E4: RENTA VARIABLE | F4: Internacional | G4: Equities | H4: USA | I4: Stock
A5: =VLOOKUP(B5,Sheet1!$A$1:$B$415,1,FALSE) -> #N/A | B5: BURL US EQUITY | C5: BURLINGTON STORES INC | D5: USD - United States Dollar | E5: RENTA VARIABLE | F5: Internacional | G5: Equities | H5: USA | I5: Stock
A6: =VLOOKUP(B6,Sheet1!$A$1:$B$415,1,FALSE) -> #N/A | B6: INFY US EQUITY | C6: INFOSYS LTD | D6: USD - United States Dollar | E6: RENTA VARIABLE | F6: Internacional | G6: Equities | H6: Asia ex Japan | I6: Stock
A7: =VLOOKUP(B7,Sheet1!$A$1:$B$415,1,FALSE) -> #N/A | B7: OS US EQUITY | C7: ONESTREAM INC | D7: USD - United States Dollar | E7: RENTA VARIABLE | F7: Internacional | G7: Equities | H7: USA | I7: Stock
A8: =VLOOKUP(B8,Sheet1!$A$1:$B$415,1,FALSE) -> #N/A | B8: MELI US EQUITY | C8: MERCADOLIBRE INC | D8: USD - United States Dollar | E8: RENTA VARIABLE | F8: Internacional | G8: Equities | H8: LATAM | I8: Stock
A9: =VLOOKUP(B9,Sheet1!$A$1:$B$415,1,FALSE) -> #N/A | B9: UBER US EQUITY | C9: UBER TECHNOLOGIES INC | D9: USD - United States Dollar | E9: RENTA VARIABLE | F9: Internacional | G9: Equities | H9: USA | I9: Stock
A10: =VLOOKUP(B10,Sheet1!$A$1:$B$415,1,FALSE) -> #N/A | B10: MNDY US EQUITY | C10: MONDAY.COM LTD | D10: USD - United States Dollar | E10: RENTA VARIABLE | F10: Internacional | G10: Equities | H10: Global | I10: Stock
A11: =VLOOKUP(B11,Sheet1!$A$1:$B$415,1,FALSE) -> #N/A | B11: MA US EQUITY | C11: MASTERCARD INC-CLASS A | D11: USD - United States Dollar | E11: RENTA VARIABLE | F11: Internacional | G11: Equities | H11: USA | I11: Stock
A12: =VLOOKUP(B12,Sheet1!$A$1:$B$415,1,FALSE) -> #N/A | B12: SNDK US EQUITY | C12: SANDISK CORP | D12: USD - United States Dollar | E12: RENTA VARIABLE | F12: Internacional | G12: Equities | H12: USA | I12: Stock
A13: =VLOOKUP(B13,Sheet1!$A$1:$B$415,1,FALSE) -> #N/A | B13: IR US EQUITY | C13: INGERSOLL-RAND PLC | D13: USD - United States Dollar | E13: RENTA VARIABLE | F13: Internacional | G13: Equities | H13: USA | I13: Stock
... A338: =VLOOKUP(B338,Sheet1!$A$1:$B$415,1,FALSE) -> #N/A | B338: ESIT GY EQUITY | C338: ISHARES MSCI EURO IT SECT ETF | D338: EUR - Euro Member Countries Euro | E338: RENTA VARIABLE | F338: Internacional | G338: Equities | H338: Europe ex UK | I338: Sector
A339: =VLOOKUP(B339,Sheet1!$A$1:$B$415,1,FALSE) -> ESJCOMR LX EQUITY | B339: ESJCOMR LX EQUITY | C339: EST INV JP SM COM FN-RUUNHD | D339: USD - United States Dollar | E339: RENTA VARIABLE | F339: Internacional | G339: Equities | H339: #NAME? | I339: Open-End Fund
A340: =VLOOKUP(B340,Sheet1!$A$1:$B$415,1,FALSE) -> #N/A | B340: ETN US EQUITY | C340: EATON CORP | D340: USD - United States Dollar | E340: RENTA VARIABLE | F340: Internacional | G340: Equities | H340: USA | I340: Stock
A341: =VLOOKUP(B341,Sheet1!$A$1:$B$415,1,FALSE) -> EWJ US EQUITY | B341: EWJ US EQUITY | C341: ISHARES MSCI JAPAN | D341: USD - United States Dollar | E341: RENTA VARIABLE | F341: Internacional | G341: Equities | H341: Japan | I341: Japan
A342: =VLOOKUP(B342,Sheet1!$A$1:$B$415,1,FALSE) -> EWJV US EQUITY | B342: EWJV US EQUITY | C342: ISHARES MSCI JAPAN VALUE ETF | D342: USD - United States Dollar | E342: RENTA VARIABLE | F342: Internacional | G342: Equities | H342: Japan | I342: Japan
A343: =VLOOKUP(B343,Sheet1!$A$1:$B$415,1,FALSE) -> EWU US EQUITY | B343: EWU US EQUITY | C343: ISHARES MSCI UNITED KINGDOM ETF | D343: USD - United States Dollar | E343: RENTA VARIABLE | F343: Internacional | G343: Equities | H343: UK | I343: UK
A344: =VLOOKUP(B344,Sheet1!$A$1:$B$415,1,FALSE) -> EWZ US EQUITY | B344: EWZ US EQUITY | C344: ISHARES BRAZIL | D344: USD - United States Dollar | E344: RENTA VARIABLE | F344: Internacional | G344: Equities | H344: LATAM | I344: Latam
A345: =VLOOKUP(B345,Sheet1!$A$1:$B$415,1,FALSE) -> FFUSGCU LX EQUITY | B345: FFUSGCU LX EQUITY | C345: JPMORGAN F-US GROWTH-D | D345: USD - United States Dollar | E345: RENTA VARIABLE | F345: Internacional | G345: Equities | H345: USA | I345: Large Cap
A346: =VLOOKUP(B346,Sheet1!$A$1:$B$415,1,FALSE) -> FFUSVCU LX EQUITY | B346: FFUSVCU LX EQUITY | C346: JPMORGAN F-JPM US VALUE-D | D346: USD - United States Dollar | E346: RENTA VARIABLE | F346: Internacional | G346: Equities | H346: USA | I346: Large Cap
A347: =VLOOKUP(B347,Sheet1!$A$1:$B$415,1,FALSE) -> FLEFAMC LX EQUITY | B347: FLEFAMC LX EQUITY | C347: JPM AMERICA EQUITY D | D347: USD - United States Dollar | E347: RENTA VARIABLE | F347: Internacional | G347: Equities | H347: USA | I347: Open-End Fund
A348: =VLOOKUP(B348,Sheet1!$A$1:$B$415,1,FALSE) -> #N/A | B348: FOFVIAU CI EQUITY | C348: FONDO DE INVERSION F2 VC III | D348: USD - United States Dollar | E348: RENTA VARIABLE | F348: Internacional | G348: Equities | H348: Asia ex Japan | I348: Sector
A349: =VLOOKUP(B349,Sheet1!$A$1:$B$415,1,FALSE) -> FRAFRAA ID EQUITY | B349: FRAFRAA ID EQUITY | C349: FRANKLIN FLOATING RATE FUND PLC A | D349: USD - United States Dollar | E349: RENTA FIJA | F349: Internacional | G349: Fixed Income | H349: US IG | I349: Fund
A350: =VLOOKUP(B350,Sheet1!$A$1:$B$415,1,FALSE) -> FRAINNA LX EQUITY | B350: FRAINNA LX EQUITY | C350: FRANKLIN INDIA FUND CLASS N | D350: USD - United States Dollar | E350: RENTA VARIABLE | F350: Internacional | G350: Equities | H350: Asia ex Japan | I350: India
A351: =VLOOKUP(B351,Sheet1!$A$1:$B$415,1,FALSE) -> FXI US EQUITY | B351: FXI US EQUITY | C351: ISHARES MSCI CHINA | D351: USD - United States Dollar | E351: RENTA VARIABLE | F351: Internacional | G351: Equities | H351: Asia ex Japan | I351: China
... A621: =VLOOKUP(B621,Sheet1!$A$1:$B$415,1,FALSE) -> #N/A | B621: XS1596778008 CORP | C621: UNICREDIT SPA 4,625% 2027 | D621: USD - United States Dollar | E621: RENTA FIJA | F621: Internacional | G621: Fixed Income | H621: Europe | I621: Bond
